PyBirdViewCode/__init__.py
PyBirdViewCode/__main__.py
PyBirdViewCode/algorithms/__init__.py
PyBirdViewCode/algorithms/base.py
PyBirdViewCode/algorithms/domination_analysis.py
PyBirdViewCode/algorithms/graph_algorithms.py
PyBirdViewCode/algorithms/pointer_analysis.py
PyBirdViewCode/algorithms/pointer_analysis_interproc.py
PyBirdViewCode/algorithms/pointer_analysis_interproc_ctx.py
PyBirdViewCode/algorithms/reaching_definition.py
PyBirdViewCode/algorithms/variable_liveness.py
PyBirdViewCode/clang_utils/__init__.py
PyBirdViewCode/clang_utils/code_attributes/__init__.py
PyBirdViewCode/clang_utils/code_attributes/extract_data_structure.py
PyBirdViewCode/clang_utils/code_attributes/extract_function_info.py
PyBirdViewCode/clang_utils/code_attributes/extract_globals.py
PyBirdViewCode/clang_utils/code_attributes/extract_statement_info.py
PyBirdViewCode/clang_utils/code_attributes/procedures.py
PyBirdViewCode/clang_utils/code_attributes/utils.py
PyBirdViewCode/clang_utils/code_attributes/stubs/cursor_kinds.py
PyBirdViewCode/clang_utils/code_attributes/stubs/update.py
PyBirdViewCode/tools_service/__init__.py
PyBirdViewCode/tools_service/base_request.py
PyBirdViewCode/tools_service/distributed_scheduler.py
PyBirdViewCode/tools_service/distributed_tool.py
PyBirdViewCode/tools_service/log.py
PyBirdViewCode/tools_service/messages.py
PyBirdViewCode/tools_service/models.py
PyBirdViewCode/tools_service/processmgr.py
PyBirdViewCode/tools_service/states.py
PyBirdViewCode/uast/__init__.py
PyBirdViewCode/uast/exceptions.py
PyBirdViewCode/uast/program_info.py
PyBirdViewCode/uast/uast_commands.py
PyBirdViewCode/uast/universal_ast_nodes.py
PyBirdViewCode/uast/universal_ast_types.py
PyBirdViewCode/uast/universal_cfg_extractor.py
PyBirdViewCode/uast/universal_code_property_graphs.py
PyBirdViewCode/uast/universal_dataflow_analysis.py
PyBirdViewCode/uast/builtin_converters/__init__.py
PyBirdViewCode/uast/builtin_converters/c_cpp_converter.py
PyBirdViewCode-0.1.0a1.dist-info/LICENSE.txt
PyBirdViewCode-0.1.0a1.dist-info/METADATA
PyBirdViewCode-0.1.0a1.dist-info/WHEEL
PyBirdViewCode-0.1.0a1.dist-info/top_level.txt
PyBirdViewCode-0.1.0a1.dist-info/RECORD
