Metadata-Version: 2.1
Name: PyBirdViewCode
Version: 0.1.0a1
Summary: A pure-python (Python>=3.10) static analysis library providing various interfaces.
Home-page: https://github.com/hzyrc6011/PyBirdViewCode
Author: hzyrc6011
Author-email: 1295752786@qq.com
License: MIT
Project-URL: Documentation, https://hzyrc6011.github.io/PyBirdViewCode/
Classifier: Development Status :: 3 - Alpha
Classifier: Intended Audience :: Science/Research
Classifier: License :: OSI Approved :: MIT License
Classifier: Natural Language :: English
Classifier: Operating System :: Unix
Classifier: Operating System :: Microsoft :: Windows
Classifier: Programming Language :: Python :: 3.10
Classifier: Programming Language :: Python :: 3.11
Classifier: Programming Language :: Python :: 3.12
Classifier: Topic :: Software Development
Classifier: Topic :: Software Development :: Libraries :: Python Modules
Requires-Python: >=3.10
License-File: LICENSE.txt
Requires-Dist: clang ~=16.0
Requires-Dist: libclang ~=16.0
Requires-Dist: six
Requires-Dist: psutil
Requires-Dist: flask
Requires-Dist: flask-sock
Requires-Dist: networkx
Requires-Dist: tqdm
Requires-Dist: MelodieFuncFlow
Requires-Dist: ply
Requires-Dist: dataclasses-json
Requires-Dist: pydot
Requires-Dist: websocket-client
Requires-Dist: requests
Requires-Dist: termcolor
Requires-Dist: strenum ; python_version <= "3.11"
